MANIFEST.in
NEWS.txt
README.rst
setup.py
src/bp/__init__.py
src/bp.preferences.egg-info/PKG-INFO
src/bp.preferences.egg-info/SOURCES.txt
src/bp.preferences.egg-info/dependency_links.txt
src/bp.preferences.egg-info/namespace_packages.txt
src/bp.preferences.egg-info/not-zip-safe
src/bp.preferences.egg-info/requires.txt
src/bp.preferences.egg-info/top_level.txt
src/bp/preferences/__init__.py