Metadata-Version: 1.0
Name: bp.preferences
Version: 0.1
Summary: Preference system for applications
Home-page: http://github.com/disko/bp.preferences
Author: Andreas Kaiser
Author-email: disko@binary-punks.com
License: BSD
Platform: UNKNOWN
